LICENSE
MANIFEST.in
README.rst
requirements.txt
setup.cfg
setup.py
zerrphix/MediainfoDLL.py
zerrphix/__init__.py
zerrphix/_version.py
zerrphix/base.py
zerrphix/config.py
zerrphix/constants.py
zerrphix/exceptions.py
zerrphix/logger.py
zerrphix/logo.png
zerrphix/manager.py
zerrphix/options.py
zerrphix/password_enc_test.py
zerrphix/plugin.py
zerrphix/pymediainfo.py
zerrphix/smbtest.py
zerrphix/temp_eapi_finder.py
zerrphix/templates.tar.gz
zerrphix/thread_reatart_test.py
zerrphix.egg-info/PKG-INFO
zerrphix.egg-info/SOURCES.txt
zerrphix.egg-info/dependency_links.txt
zerrphix.egg-info/entry_points.txt
zerrphix.egg-info/not-zip-safe
zerrphix.egg-info/requires.txt
zerrphix.egg-info/top_level.txt
zerrphix/alembic/README
zerrphix/alembic/__init__.py
zerrphix/alembic/env.py
zerrphix/alembic/script.py.mako
zerrphix/alembic/versions/1c079b6b4eff_redo_zp_res.py
zerrphix/alembic/versions/49823d4740a2_add_table_zp_vcodec.py
zerrphix/alembic/versions/4fcc62ce28dc_add_zp_tcodec.py
zerrphix/alembic/versions/6b75323b6c7d_add_temaplte_sha256_column_to_zp_.py
zerrphix/alembic/versions/71047edd5449_add_bitrate_column_to_zp_film_.py
zerrphix/alembic/versions/__init__.py
zerrphix/alembic/versions/c0d1fa61980d_change_pk_of_zp_db_log.py
zerrphix/alembic/versions/c640c1ca3402_add_gsm610_to_zp_acodec.py
zerrphix/alembic/versions/d9d26cdee08b_add_width_and_height_columns_to_zp_film_.py
zerrphix/alembic/versions/f5c805cabe49_redo_zp_audio_to_add_score_column.py
zerrphix/artwork/__init__.py
zerrphix/db/__init__.py
zerrphix/db/tables.py
zerrphix/film/__init__.py
zerrphix/film/artwork.py
zerrphix/film/artwork_collection.py
zerrphix/film/artwork_user.py
zerrphix/film/base.py
zerrphix/film/data.py
zerrphix/film/identify.py
zerrphix/film/inverse_scan.py
zerrphix/film/metadata.py
zerrphix/film/raw_collection_images.py
zerrphix/film/raw_images.py
zerrphix/film/scan.py
zerrphix/film/score.py
zerrphix/film/tidyup.py
zerrphix/film/user_specifics.py
zerrphix/film/util.py
zerrphix/httpserver/__init__.py
zerrphix/httpserver/admin/__init__.py
zerrphix/httpserver/admin/adminhttpsrv.py
zerrphix/httpserver/admin/api.py
zerrphix/httpserver/admin/base.py
zerrphix/httpserver/admin/dunes.py
zerrphix/httpserver/admin/film.py
