Metadata-Version: 1.1
Name: zerrphix
Version: 0.1.8.dev12
Summary: Zerrphix is for HDI DUNE network media players that can utilise the dune_http:// functionality
Home-page: https://github.com/3lixy/Zerrphix
Author: Zerrphix Project
Author-email: zerrphix.project@gmail.com
License: MIT
Platform: UNKNOWN
Classifier: Development Status :: 4 - Beta
Classifier: License :: OSI Approved :: MIT License
Classifier: Operating System :: Unix
Classifier: Programming Language :: Python
Classifier: Programming Language :: Python :: 2.7
